rossum_mcp/__init__.py
rossum_mcp/logging_config.py
rossum_mcp/py.typed
rossum_mcp/server.py
rossum_mcp/tools/__init__.py
rossum_mcp/tools/annotations.py
rossum_mcp/tools/base.py
rossum_mcp/tools/catalog.py
rossum_mcp/tools/discovery.py
rossum_mcp/tools/document_relations.py
rossum_mcp/tools/email_templates.py
rossum_mcp/tools/engines.py
rossum_mcp/tools/hooks.py
rossum_mcp/tools/queues.py
rossum_mcp/tools/relations.py
rossum_mcp/tools/rules.py
rossum_mcp/tools/schemas.py
rossum_mcp/tools/users.py
rossum_mcp/tools/workspaces.py
rossum_mcp-1.0.1.dist-info/licenses/LICENSE
rossum_mcp-1.0.1.dist-info/METADATA
rossum_mcp-1.0.1.dist-info/WHEEL
rossum_mcp-1.0.1.dist-info/entry_points.txt
rossum_mcp-1.0.1.dist-info/top_level.txt
rossum_mcp-1.0.1.dist-info/RECORD
