Metadata-Version: 2.4
Name: rossum-mcp
Version: 1.0.1
Summary: MCP server for AI-powered Rossum orchestration: document workflows, debug pipelines automatically, and configure intelligent document processing through natural language.
Author-email: "Dan Stancl (Rossum AI)" <daniel.stancl@gmail.com>
License: MIT
Keywords: mcp,rossum,document-processing
Classifier: Development Status :: 5 - Production/Stable
Classifier: License :: OSI Approved :: MIT License
Classifier: Programming Language :: Python :: 3
Classifier: Programming Language :: Python :: 3.12
Classifier: Programming Language :: Python :: 3.13
Classifier: Programming Language :: Python :: 3.14
Classifier: Intended Audience :: Developers
Classifier: Topic :: Scientific/Engineering :: Artificial Intelligence
Classifier: Topic :: Software Development :: Libraries :: Python Modules
Requires-Python: >=3.12
License-File: LICENSE
Requires-Dist: fastmcp>=2.0.0
Requires-Dist: pydantic>2.0.0
Requires-Dist: rossum-api>=3.8.0
Provides-Extra: docs
Requires-Dist: myst-parser>=2.0.0; extra == "docs"
Requires-Dist: sphinx>=7.0.0; extra == "docs"
Requires-Dist: sphinx-autodoc-typehints>=1.25.0; extra == "docs"
Requires-Dist: sphinx-copybutton>=0.5.2; extra == "docs"
Requires-Dist: sphinx-rtd-theme>=2.0.0; extra == "docs"
Provides-Extra: tests
Requires-Dist: coverage>=7.0.0; extra == "tests"
Requires-Dist: pytest>=7.0.0; extra == "tests"
Requires-Dist: pytest-asyncio>=0.21.0; extra == "tests"
Requires-Dist: pytest-cov>=4.0.0; extra == "tests"
Requires-Dist: redis>=7.0.0; extra == "tests"
Provides-Extra: all
Requires-Dist: coverage>=7.0.0; extra == "all"
Requires-Dist: fastmcp>=2.0.0; extra == "all"
Requires-Dist: myst-parser>=2.0.0; extra == "all"
Requires-Dist: pydantic>2.0.0; extra == "all"
Requires-Dist: pytest>=7.0.0; extra == "all"
Requires-Dist: pytest-asyncio>=0.21.0; extra == "all"
Requires-Dist: redis>=7.0.0; extra == "all"
Requires-Dist: rossum-api>=3.8.0; extra == "all"
Requires-Dist: sphinx>=7.0.0; extra == "all"
Requires-Dist: sphinx-autodoc-typehints>=1.25.0; extra == "all"
Requires-Dist: sphinx-copybutton>=0.5.2; extra == "all"
Requires-Dist: sphinx-rtd-theme>=2.0.0; extra == "all"
Dynamic: license-file
